puan_db_pb2.py
puan_db_pb2.pyi
puan_db_pb2_grpc.py
puan_db_python/__init__.py
puan_db_python-0.1.41.dist-info/METADATA
puan_db_python-0.1.41.dist-info/WHEEL
puan_db_python-0.1.41.dist-info/RECORD
