Metadata-Version: 2.1
Name: puan-db-python
Version: 0.1.41
Summary: 
Author: znittzel
Author-email: rikard@ourstudio.se
Requires-Python: >=3.9,<4.0
Classifier: Programming Language :: Python :: 3
Classifier: Programming Language :: Python :: 3.9
Classifier: Programming Language :: Python :: 3.10
Classifier: Programming Language :: Python :: 3.11
Classifier: Programming Language :: Python :: 3.12
Requires-Dist: grpcio (>=1.62.2,<2.0.0)
Requires-Dist: grpcio-tools (>=1.62.2,<2.0.0)
